autocalver/__init__.py
autocalver/integration.py
autocalver-2023.5.4.55367.dist-info/LICENSE
autocalver-2023.5.4.55367.dist-info/METADATA
autocalver-2023.5.4.55367.dist-info/WHEEL
autocalver-2023.5.4.55367.dist-info/entry_points.txt
autocalver-2023.5.4.55367.dist-info/top_level.txt
autocalver-2023.5.4.55367.dist-info/RECORD
